{
  "name": "Field Visualisation (Grid)",
  "nickname": "Field Grid",
  "icon": "icon_field_grid_vis.png",
  "description": "Translate a field into a grid based visualisation. Outputs a number constrained by a range which can be used to then make a color or shape.",
  "category": "Groundhog",
  "subcategory": "Mapping",
  "inputs": [
    {
      "name": "Field",
      "id": "F",
      "description": "Field generated by a Field Component",
      "optional": false,
      "type": "Surface"
    },
    {
      "name": "Bounds",
      "id": "B",
      "description": "Curve boundary to constraint the visualisation to a certain area",
      "optional": false,
      "type": "Curve",
      "Optional": true
    },
    {
      "name": "Domain Start",
      "id": "DS",
      "description": "Starting value representing the 'bottom' value",
      "optional": false,
      "type": "Number",
      "Optional": true
    },
    {
      "name": "Domain End",
      "id": "DE",
      "description": "Ending value representing the 'top' value",
      "optional": false,
      "type": "Number",
      "Optional": true
    }
  ],
  "outputs": [
    {
      "name": "Points",
      "id": "P",
      "description": "Grid Points",
      "optional": false,
      "type": "Point"
    },
    {
      "name": "Parameters",
      "id": "P",
      "description": "Grid Parameters",
      "optional": false,
      "type": "NumberParameter(\"Parameters\", \"P\", \"Grid "
    }
  ]
}